conf/__init__.py
conf/settings.py
conf/urls.py
conf/wsgi.py
djimage/__init__.py
djimage/apps.py
djimage/field.py
testapp/__init__.py
testapp/admin.py
testapp/apps.py
testapp/models.py
testapp/tests.py
testapp/views.py
testapp/migrations/0001_initial.py
testapp/migrations/__init__.py
Djimage-0.0.1.dist-info/METADATA
Djimage-0.0.1.dist-info/WHEEL
Djimage-0.0.1.dist-info/top_level.txt
Djimage-0.0.1.dist-info/RECORD
